applipy_metrics/__init__.py
applipy_metrics/chronometer.py
applipy_metrics/decorators.py
applipy_metrics/module.py
applipy_metrics/registry.py
applipy_metrics/version.py
applipy_metrics/meters/__init__.py
applipy_metrics/meters/base_metric.py
applipy_metrics/meters/counter.py
applipy_metrics/meters/gauge.py
applipy_metrics/meters/summary.py
applipy_metrics/reporters/__init__.py
applipy_metrics/reporters/console_reporter.py
applipy_metrics/reporters/newrelic_reporter.py
applipy_metrics/reporters/reporter.py
applipy_metrics/reporters/syslog_reporter.py
applipy_metrics/stats/__init__.py
applipy_metrics/stats/moving_average.py
applipy_metrics/stats/samples.py
applipy_metrics/stats/snapshot.py
applipy_metrics-1.2.3.dist-info/LICENSE
applipy_metrics-1.2.3.dist-info/METADATA
applipy_metrics-1.2.3.dist-info/WHEEL
applipy_metrics-1.2.3.dist-info/top_level.txt
applipy_metrics-1.2.3.dist-info/RECORD
